SASCRiP/AddHGNC_features.R
SASCRiP/MultipleSample_cqc_vis.R
SASCRiP/__init__.py
SASCRiP/cqc_srt.R
SASCRiP/cut_t2g.sh
SASCRiP/edit_fastq_function.sh
SASCRiP/edit_seurat_matrix.sh
SASCRiP/gen_func.py
SASCRiP/install_packages.R
SASCRiP/logNorm_seurat.R
SASCRiP/normalise_seurat.R
SASCRiP/sascrip_functions.py
SASCRiP-1.2.3.dist-info/METADATA
SASCRiP-1.2.3.dist-info/WHEEL
SASCRiP-1.2.3.dist-info/top_level.txt
SASCRiP-1.2.3.dist-info/RECORD
