Metadata-Version: 2.1
Name: SASCRiP
Version: 1.2.3
Summary: A python package with wrapper functions that use the widely used Seurat and BUStools to perform single-cell RNA sequencing data pre-processing and visualisation
Home-page: https://github.com/Darisia/SASCRiP
Author: Darisia Moonsamy
Author-email: darisia@outlook.com
License: UNKNOWN
Keywords: single-cell RNA sequencing,data pre-processing,wrapper functions
Platform: UNKNOWN
Classifier: License :: OSI Approved :: GNU Affero General Public License v3
Classifier: Natural Language :: English
Classifier: Operating System :: Unix
Classifier: Programming Language :: Python
Classifier: Programming Language :: Python :: 3
Classifier: Programming Language :: R
Classifier: Programming Language :: Unix Shell
Requires-Python: >=3.7
Requires-Dist: Kb-python (==0.24.1)
